Workbook

Sheet Assumptions
A1: Loan & Investment Assumptions
A2: Yellow cells are inputs — change them and every sheet recalculates.
A4: Input | B4: Value
A5: Loan principal | B5: 320000
A6: Annual interest rate | B6: 0.065
A7: Term (years) | B7: 30
A8: Extra principal / month | B8: 200
A9: Investment return (annual) | B9: 0.07
A11: Derived
A12: Monthly rate | B12: =Assumptions!$B$6/12
A13: Number of payments | B13: =Assumptions!$B$7*12
A14: Monthly payment | B14: =-PMT(Assumptions!$B$6/12,Assumptions!$B$7*12,Assumptions!$B$5)
A15: Payment + extra | B15: =B13+Assumptions!$B$8

Sheet Summary
A1: Results
A2: Every figure below is a formula over the two schedules.
A4: Metric | B4: Standard | C4: With extra
A5: Monthly payment | B5: =Assumptions!$B$13 | C5: =Assumptions!$B$14
A6: Months to payoff | B6: =COUNTIF(Amortization!C4:C363,">0") | C6: =COUNTIF('With Extra Payment'!C4:C363,">0")
A7: Years to payoff | B7: =B6/12 | C7: =C6/12
A8: Total interest | B8: =SUM(Amortization!D4:D363) | C8: =SUM('With Extra Payment'!D4:D363)
A9: Total paid | B9: =Assumptions!$B$5+B8 | C9: =Assumptions!$B$5+C8
A11: Effect of the extra payment
A12: Interest saved | B12: =B8-C8
A13: Months saved | B13: =B6-C6
A14: Years saved | B14: =(B6-C6)/12
A16: Prepay vs. invest — equal monthly outflow, valued at month 360
A17: Both paths spend the same amount every month. Invest: pay the scheduled payment for all 360 months and invest the extra. Prepay: pay extra until the loan ends, then invest the whole freed-up payment.
A19: Invest the extra for 360 months | B19: =FV(Assumptions!$B$9/12,Assumptions!$B$7*12,-Assumptions!$B$8,0)
A20: Prepay, then invest the payment | B20: =FV(Assumptions!$B$9/12,B13,-Assumptions!$B$14,0)
A21: Advantage of investing | B21: =B19-B20

Sheet Amortization
A1: Standard schedule — scheduled payment only
A3: Month | B3: Opening balance | C3: Payment | D3: Interest | E3: Principal | F3: Closing balance | G3: Cumulative interest
A4: 1 | B4: =IF(Assumptions!$B$5<=0,0,Assumptions!$B$5) | C4: =IF(B4<=0,0,MIN(Assumptions!$B$13,B4+D4)) | D4: =IF(B4<=0,0,B4*Assumptions!$B$6/12) | E4: =IF(B4<=0,0,C4-D4) | F4: =IF(B4<=0,0,B4-E4) | G4: =IF(B4<=0,G3,D4)
A5: 2 | B5: =IF(F4<=0,0,F4) | C5: =IF(B5<=0,0,MIN(Assumptions!$B$13,B5+D5)) | D5: =IF(B5<=0,0,B5*Assumptions!$B$6/12) | E5: =IF(B5<=0,0,C5-D5) | F5: =IF(B5<=0,0,B5-E5) | G5: =IF(B5<=0,G4,G4+D5)
A6: 3 | B6: =IF(F5<=0,0,F5) | C6: =IF(B6<=0,0,MIN(Assumptions!$B$13,B6+D6)) | D6: =IF(B6<=0,0,B6*Assumptions!$B$6/12) | E6: =IF(B6<=0,0,C6-D6) | F6: =IF(B6<=0,0,B6-E6) | G6: =IF(B6<=0,G5,G5+D6)
A7: 4 | B7: =IF(F6<=0,0,F6) | C7: =IF(B7<=0,0,MIN(Assumptions!$B$13,B7+D7)) | D7: =IF(B7<=0,0,B7*Assumptions!$B$6/12) | E7: =IF(B7<=0,0,C7-D7) | F7: =IF(B7<=0,0,B7-E7) | G7: =IF(B7<=0,G6,G6+D7)
A8: 5 | B8: =IF(F7<=0,0,F7) | C8: =IF(B8<=0,0,MIN(Assumptions!$B$13,B8+D8)) | D8: =IF(B8<=0,0,B8*Assumptions!$B$6/12) | E8: =IF(B8<=0,0,C8-D8) | F8: =IF(B8<=0,0,B8-E8) | G8: =IF(B8<=0,G7,G7+D8)
A9: 6 | B9: =IF(F8<=0,0,F8) | C9: =IF(B9<=0,0,MIN(Assumptions!$B$13,B9+D9)) | D9: =IF(B9<=0,0,B9*Assumptions!$B$6/12) | E9: =IF(B9<=0,0,C9-D9) | F9: =IF(B9<=0,0,B9-E9) | G9: =IF(B9<=0,G8,G8+D9)
A10: 7 | B10: =IF(F9<=0,0,F9) | C10: =IF(B10<=0,0,MIN(Assumptions!$B$13,B10+D10)) | D10: =IF(B10<=0,0,B10*Assumptions!$B$6/12) | E10: =IF(B10<=0,0,C10-D10) | F10: =IF(B10<=0,0,B10-E10) | G10: =IF(B10<=0,G9,G9+D10)
A11: 8 | B11: =IF(F10<=0,0,F10) | C11: =IF(B11<=0,0,MIN(Assumptions!$B$13,B11+D11)) | D11: =IF(B11<=0,0,B11*Assumptions!$B$6/12) | E11: =IF(B11<=0,0,C11-D11) | F11: =IF(B11<=0,0,B11-E11) | G11: =IF(B11<=0,G10,G10+D11)
A12: 9 | B12: =IF(F11<=0,0,F11) | C12: =IF(B12<=0,0,MIN(Assumptions!$B$13,B12+D12)) | D12: =IF(B12<=0,0,B12*Assumptions!$B$6/12) | E12: =IF(B12<=0,0,C12-D12) | F12: =IF(B12<=0,0,B12-E12) | G12: =IF(B12<=0,G11,G11+D12)
A13: 10 | B13: =IF(F12<=0,0,F12) | C13: =IF(B13<=0,0,MIN(Assumptions!$B$13,B13+D13)) | D13: =IF(B13<=0,0,B13*Assumptions!$B$6/12) | E13: =IF(B13<=0,0,C13-D13) | F13: =IF(B13<=0,0,B13-E13) | G13: =IF(B13<=0,G12,G12+D13)
A14: 11 | B14: =IF(F13<=0,0,F13) | C14: =IF(B14<=0,0,MIN(Assumptions!$B$13,B14+D14)) | D14: =IF(B14<=0,0,B14*Assumptions!$B$6/12) | E14: =IF(B14<=0,0,C14-D14) | F14: =IF(B14<=0,0,B14-E14) | G14: =IF(B14<=0,G13,G13+D14)
A15: 12 | B15: =IF(F14<=0,0,F14) | C15: =IF(B15<=0,0,MIN(Assumptions!$B$13,B15+D15)) | D15: =IF(B15<=0,0,B15*Assumptions!$B$6/12) | E15: =IF(B15<=0,0,C15-D15) | F15: =IF(B15<=0,0,B15-E15) | G15: =IF(B15<=0,G14,G14+D15)
A16: 13 | B16: =IF(F15<=0,0,F15) | C16: =IF(B16<=0,0,MIN(Assumptions!$B$13,B16+D16)) | D16: =IF(B16<=0,0,B16*Assumptions!$B$6/12) | E16: =IF(B16<=0,0,C16-D16) | F16: =IF(B16<=0,0,B16-E16) | G16: =IF(B16<=0,G15,G15+D16)
... A363: 360 | B363: =IF(F362<=0,0,F362) | C363: =IF(B363<=0,0,MIN(Assumptions!$B$13,B363+D363)) | D363: =IF(B363<=0,0,B363*Assumptions!$B$6/12) | E363: =IF(B363<=0,0,C363-D363) | F363: =IF(B363<=0,0,B363-E363) | G363: =IF(B363<=0,G362,G362+D363)

Sheet With Extra Payment
A1: Accelerated schedule — scheduled payment plus extra principal
A3: Month | B3: Opening balance | C3: Payment | D3: Interest | E3: Principal | F3: Closing balance | G3: Cumulative interest
A4: 1 | B4: =IF(Assumptions!$B$5<=0,0,Assumptions!$B$5) | C4: =IF(B4<=0,0,MIN(Assumptions!$B$14,B4+D4)) | D4: =IF(B4<=0,0,B4*Assumptions!$B$6/12) | E4: =IF(B4<=0,0,C4-D4) | F4: =IF(B4<=0,0,B4-E4) | G4: =IF(B4<=0,G3,D4)
A5: 2 | B5: =IF(F4<=0,0,F4) | C5: =IF(B5<=0,0,MIN(Assumptions!$B$14,B5+D5)) | D5: =IF(B5<=0,0,B5*Assumptions!$B$6/12) | E5: =IF(B5<=0,0,C5-D5) | F5: =IF(B5<=0,0,B5-E5) | G5: =IF(B5<=0,G4,G4+D5)
A6: 3 | B6: =IF(F5<=0,0,F5) | C6: =IF(B6<=0,0,MIN(Assumptions!$B$14,B6+D6)) | D6: =IF(B6<=0,0,B6*Assumptions!$B$6/12) | E6: =IF(B6<=0,0,C6-D6) | F6: =IF(B6<=0,0,B6-E6) | G6: =IF(B6<=0,G5,G5+D6)
A7: 4 | B7: =IF(F6<=0,0,F6) | C7: =IF(B7<=0,0,MIN(Assumptions!$B$14,B7+D7)) | D7: =IF(B7<=0,0,B7*Assumptions!$B$6/12) | E7: =IF(B7<=0,0,C7-D7) | F7: =IF(B7<=0,0,B7-E7) | G7: =IF(B7<=0,G6,G6+D7)
A8: 5 | B8: =IF(F7<=0,0,F7) | C8: =IF(B8<=0,0,MIN(Assumptions!$B$14,B8+D8)) | D8: =IF(B8<=0,0,B8*Assumptions!$B$6/12) | E8: =IF(B8<=0,0,C8-D8) | F8: =IF(B8<=0,0,B8-E8) | G8: =IF(B8<=0,G7,G7+D8)
A9: 6 | B9: =IF(F8<=0,0,F8) | C9: =IF(B9<=0,0,MIN(Assumptions!$B$14,B9+D9)) | D9: =IF(B9<=0,0,B9*Assumptions!$B$6/12) | E9: =IF(B9<=0,0,C9-D9) | F9: =IF(B9<=0,0,B9-E9) | G9: =IF(B9<=0,G8,G8+D9)
A10: 7 | B10: =IF(F9<=0,0,F9) | C10: =IF(B10<=0,0,MIN(Assumptions!$B$14,B10+D10)) | D10: =IF(B10<=0,0,B10*Assumptions!$B$6/12) | E10: =IF(B10<=0,0,C10-D10) | F10: =IF(B10<=0,0,B10-E10) | G10: =IF(B10<=0,G9,G9+D10)
A11: 8 | B11: =IF(F10<=0,0,F10) | C11: =IF(B11<=0,0,MIN(Assumptions!$B$14,B11+D11)) | D11: =IF(B11<=0,0,B11*Assumptions!$B$6/12) | E11: =IF(B11<=0,0,C11-D11) | F11: =IF(B11<=0,0,B11-E11) | G11: =IF(B11<=0,G10,G10+D11)
A12: 9 | B12: =IF(F11<=0,0,F11) | C12: =IF(B12<=0,0,MIN(Assumptions!$B$14,B12+D12)) | D12: =IF(B12<=0,0,B12*Assumptions!$B$6/12) | E12: =IF(B12<=0,0,C12-D12) | F12: =IF(B12<=0,0,B12-E12) | G12: =IF(B12<=0,G11,G11+D12)
A13: 10 | B13: =IF(F12<=0,0,F12) | C13: =IF(B13<=0,0,MIN(Assumptions!$B$14,B13+D13)) | D13: =IF(B13<=0,0,B13*Assumptions!$B$6/12) | E13: =IF(B13<=0,0,C13-D13) | F13: =IF(B13<=0,0,B13-E13) | G13: =IF(B13<=0,G12,G12+D13)
A14: 11 | B14: =IF(F13<=0,0,F13) | C14: =IF(B14<=0,0,MIN(Assumptions!$B$14,B14+D14)) | D14: =IF(B14<=0,0,B14*Assumptions!$B$6/12) | E14: =IF(B14<=0,0,C14-D14) | F14: =IF(B14<=0,0,B14-E14) | G14: =IF(B14<=0,G13,G13+D14)
A15: 12 | B15: =IF(F14<=0,0,F14) | C15: =IF(B15<=0,0,MIN(Assumptions!$B$14,B15+D15)) | D15: =IF(B15<=0,0,B15*Assumptions!$B$6/12) | E15: =IF(B15<=0,0,C15-D15) | F15: =IF(B15<=0,0,B15-E15) | G15: =IF(B15<=0,G14,G14+D15)
A16: 13 | B16: =IF(F15<=0,0,F15) | C16: =IF(B16<=0,0,MIN(Assumptions!$B$14,B16+D16)) | D16: =IF(B16<=0,0,B16*Assumptions!$B$6/12) | E16: =IF(B16<=0,0,C16-D16) | F16: =IF(B16<=0,0,B16-E16) | G16: =IF(B16<=0,G15,G15+D16)
... A363: 360 | B363: =IF(F362<=0,0,F362) | C363: =IF(B363<=0,0,MIN(Assumptions!$B$14,B363+D363)) | D363: =IF(B363<=0,0,B363*Assumptions!$B$6/12) | E363: =IF(B363<=0,0,C363-D363) | F363: =IF(B363<=0,0,B363-E363) | G363: =IF(B363<=0,G362,G362+D363)

Sheet Rate Sensitivity
A1: Payment and total interest across rates
A2: Recomputed independently of the schedules, so it stays live too.
A4: Rate | B4: Monthly payment | C4: Total interest | D4: vs. base rate
A5: 0.045 | B5: =-PMT(A5/12,Assumptions!$B$7*12,Assumptions!$B$5) | C5: =B5*Assumptions!$B$7*12-Assumptions!$B$5 | D5: =C5-(-PMT(Assumptions!$B$6/12,Assumptions!$B$7*12,Assumptions!$B$5)*Assumptions!$B$7*12-Assumptions!$B$5)
A6: 0.05 | B6: =-PMT(A6/12,Assumptions!$B$7*12,Assumptions!$B$5) | C6: =B6*Assumptions!$B$7*12-Assumptions!$B$5 | D6: =C6-(-PMT(Assumptions!$B$6/12,Assumptions!$B$7*12,Assumptions!$B$5)*Assumptions!$B$7*12-Assumptions!$B$5)
A7: 0.055 | B7: =-PMT(A7/12,Assumptions!$B$7*12,Assumptions!$B$5) | C7: =B7*Assumptions!$B$7*12-Assumptions!$B$5 | D7: =C7-(-PMT(Assumptions!$B$6/12,Assumptions!$B$7*12,Assumptions!$B$5)*Assumptions!$B$7*12-Assumptions!$B$5)
A8: 0.06 | B8: =-PMT(A8/12,Assumptions!$B$7*12,Assumptions!$B$5) | C8: =B8*Assumptions!$B$7*12-Assumptions!$B$5 | D8: =C8-(-PMT(Assumptions!$B$6/12,Assumptions!$B$7*12,Assumptions!$B$5)*Assumptions!$B$7*12-Assumptions!$B$5)
A9: 0.065 | B9: =-PMT(A9/12,Assumptions!$B$7*12,Assumptions!$B$5) | C9: =B9*Assumptions!$B$7*12-Assumptions!$B$5 | D9: =C9-(-PMT(Assumptions!$B$6/12,Assumptions!$B$7*12,Assumptions!$B$5)*Assumptions!$B$7*12-Assumptions!$B$5)
A10: 0.07 | B10: =-PMT(A10/12,Assumptions!$B$7*12,Assumptions!$B$5) | C10: =B10*Assumptions!$B$7*12-Assumptions!$B$5 | D10: =C10-(-PMT(Assumptions!$B$6/12,Assumptions!$B$7*12,Assumptions!$B$5)*Assumptions!$B$7*12-Assumptions!$B$5)
A11: 0.075 | B11: =-PMT(A11/12,Assumptions!$B$7*12,Assumptions!$B$5) | C11: =B11*Assumptions!$B$7*12-Assumptions!$B$5 | D11: =C11-(-PMT(Assumptions!$B$6/12,Assumptions!$B$7*12,Assumptions!$B$5)*Assumptions!$B$7*12-Assumptions!$B$5)
A12: 0.08 | B12: =-PMT(A12/12,Assumptions!$B$7*12,Assumptions!$B$5) | C12: =B12*Assumptions!$B$7*12-Assumptions!$B$5 | D12: =C12-(-PMT(Assumptions!$B$6/12,Assumptions!$B$7*12,Assumptions!$B$5)*Assumptions!$B$7*12-Assumptions!$B$5)
A13: 0.085 | B13: =-PMT(A13/12,Assumptions!$B$7*12,Assumptions!$B$5) | C13: =B13*Assumptions!$B$7*12-Assumptions!$B$5 | D13: =C13-(-PMT(Assumptions!$B$6/12,Assumptions!$B$7*12,Assumptions!$B$5)*Assumptions!$B$7*12-Assumptions!$B$5)
A14: 0.09 | B14: =-PMT(A14/12,Assumptions!$B$7*12,Assumptions!$B$5) | C14: =B14*Assumptions!$B$7*12-Assumptions!$B$5 | D14: =C14-(-PMT(Assumptions!$B$6/12,Assumptions!$B$7*12,Assumptions!$B$5)*Assumptions!$B$7*12-Assumptions!$B$5)
A15: 0.095 | B15: =-PMT(A15/12,Assumptions!$B$7*12,Assumptions!$B$5) | C15: =B15*Assumptions!$B$7*12-Assumptions!$B$5 | D15: =C15-(-PMT(Assumptions!$B$6/12,Assumptions!$B$7*12,Assumptions!$B$5)*Assumptions!$B$7*12-Assumptions!$B$5)
